{
  "users": [
    {
      "firstName": "Shirish",
      "lastName": "Shrestha",
      "emailAddress": "shrestha@gmail.com",
      "userName": "shirish",
      "password": "shirish",
      "id": 4
    }
  ],
  "investments": [
    {
      "userId": 4,
      "symbol": "AAPL",
      "stockName": "Apple, Inc.",
      "purchasePrice": 248.76,
      "purchaseQty": "4.01994",
      "totalPrice": "1000",
      "purchaseDate": 1572583726026,
      "parentId": 0,
      "id": 1
    },
    {
      "symbol": "FB",
      "stockName": "Facebook, Inc.",
      "purchasePrice": 191.65,
      "purchaseQty": "5.21785",
      "totalPrice": "1000",
      "parentId": 0,
      "purchaseDate": 1572583925522,
      "userId": "4",
      "id": 4
    },
    {
      "userId": 4,
      "symbol": "MSFT",
      "stockName": "Microsoft Corp.",
      "purchasePrice": 150.39,
      "purchaseQty": "50",
      "totalPrice": "7519.50000",
      "purchaseDate": 1574215637950,
      "parentId": 0,
      "id": 5
    },
    {
      "symbol": "BABA",
      "stockName": "Alibaba Group Holding Ltd.",
      "purchasePrice": 185.25,
      "purchaseQty": "40.59109",
      "totalPrice": "7519.50000",
      "parentId": 5,
      "purchaseDate": 1574215688539,
      "userId": "4",
      "id": 6
    }
  ],
  "watchlists": [
    {
      "userId": 4,
      "symbol": "BABA",
      "stockName": "Alibaba Group Holding Ltd.",
      "id": 6
    }
  ]
}